Flask_GzipBomb-0.1.0.dist-info/DESCRIPTION.rst
Flask_GzipBomb-0.1.0.dist-info/METADATA
Flask_GzipBomb-0.1.0.dist-info/RECORD
Flask_GzipBomb-0.1.0.dist-info/WHEEL
Flask_GzipBomb-0.1.0.dist-info/metadata.json
Flask_GzipBomb-0.1.0.dist-info/top_level.txt
flask_gzipbomb/__init__.py
flask_gzipbomb/_rawdata.py
