Metadata-Version: 2.0
Name: Flask-GzipBomb
Version: 0.1.0
Summary: Gzip Bomb responses for Flask
Home-page: https://github.com/kuszaj/Flask-GzipBomb
Author: Piotr Kuszaj
Author-email: peterkuszaj@gmail.com
License: MIT
Download-URL: https://github.com/kuszaj/Flask-GzipBomb/archive/v0.1.0.tar.gz
Platform: any
Classifier: Environment :: Web Environment
Classifier: Intended Audience :: Developers
Classifier: License :: OSI Approved :: MIT License
Classifier: Operating System :: OS Independent
Classifier: Programming Language :: Python
Classifier: Topic :: Internet :: WWW/HTTP :: Dynamic Content
Classifier: Topic :: Software Development :: Libraries :: Python Modules
Requires-Dist: Flask
